modal_utilities/__init__.py
modal_utilities/cli.py
modal_utilities/configuration.py
modal_utilities/refresh.py
modal_utilities/volumes.py
modal_utilities-0.1.7.dist-info/METADATA
modal_utilities-0.1.7.dist-info/WHEEL
modal_utilities-0.1.7.dist-info/top_level.txt
modal_utilities-0.1.7.dist-info/RECORD
