Metadata-Version: 2.4
Name: modal-utilities
Version: 0.1.7
Summary: Modal utilities
Author: Kayvon Tabrizi
License-Expression: MIT
Project-URL: Homepage, https://github.com/kayvontabrizi/modal-utilities
Classifier: Programming Language :: Python :: 3
Requires-Python: >=3.10
Requires-Dist: modal
